pymath/interval/__init__.py
pymath/interval/imath.py
pymath/interval/integral.py
pymath/interval/ioperator.py
pymath/interval/root_all.py
pymath/interval/_src/__init__.py
pymath/interval/_src/fpu_rounding.py
pymath/interval/_src/imath.py
pymath/interval/_src/interval.py
pymath/interval/_src/lanczos.py
pymath/interval/_src/max_in.py
pymath/interval/_src/root_all.py
pymath/interval/_src/typing.py
pymath_interval-0.4.3.dist-info/LICENSE
pymath_interval-0.4.3.dist-info/METADATA
pymath_interval-0.4.3.dist-info/WHEEL
pymath_interval-0.4.3.dist-info/top_level.txt
pymath_interval-0.4.3.dist-info/RECORD
